{
  "bench_config": {
    "process_count": 8,
    "problem": {
      "name": "kroA100",
      "optimal_length": 21282
    },
    "algorithm": "CABC",
    "algorithm_constants": {
      "max_iterations": 4000,
      "colony_size": 20,
      "exchange_generations": 8,
      "nl_max": 5,
      "p_cp": 0.8,
      "p_rc": 0.5,
      "p_l": 0.2,
      "l_min": 2,
      "l_max_mul": 0.5,
      "r": 1.0,
      "capital_l": 3.0,
      "lowercase_q": 3,
      "k": 16.0
    },
    "benchmark_start_time_millis": 1684570669935,
    "repeat_times": 10
  },
  "benchmark_duration_millis": 1375,
  "run_results": [
    {
      "run_number": 0,
      "found_optimal_tour": false,
      "shortest_found_tour": 21292,
      "iteration_reached": 4000,
      "shortest_iteration_tours": [
        [
          2,
          26231
        ],
        [
          3,
          25877
        ],
        [
          8,
          24698
        ],
        [
          9,
          25617
        ],
        [
          12,
          25516
        ],
        [
          16,
          24311
        ],
        [
          17,
          24698
        ],
        [
          23,
          24435
        ],
        [
          24,
          24166
        ],
        [
          32,
          23982
        ],
        [
          33,
          24157
        ],
        [
          48,
          23329
        ],
        [
          54,
          24120
        ],
        [
          57,
          23892
        ],
        [
          64,
          23158
        ],
        [
          65,
          23329
        ],
        [
          66,
          23261
        ],
        [
          80,
          22862
        ],
        [
          86,
          22991
        ],
        [
          88,
          22733
        ],
        [
          89,
          22862
        ],
        [
          92,
          22744
        ],
        [
          96,
          22697
        ],
        [
          97,
          22733
        ],
        [
          104,
          22433
        ],
        [
          107,
          22692
        ],
        [
          112,
          22282
        ],
        [
          120,
          22155
        ],
        [
          121,
          22583
        ],
        [
          129,
          22155
        ],
        [
          136,
          22114
        ],
        [
          139,
          22144
        ],
        [
          153,
          22114
        ],
        [
          154,
          22052
        ],
        [
          160,
          22052
        ],
        [
          161,
          22041
        ],
        [
          168,
          22041
        ],
        [
          171,
          22029
        ],
        [
          176,
          21989
        ],
        [
          184,
          21960
        ],
        [
          185,
          21996
        ],
        [
          190,
          21866
        ],
        [
          192,
          21768
        ],
        [
          197,
          21854
        ],
        [
          201,
          21768
        ],
        [
          208,
          21582
        ],
        [
          209,
          21582
        ],
        [
          224,
          21553
        ],
        [
          225,
          21553
        ],
        [
          232,
          21483
        ],
        [
          233,
          21483
        ],
        [
          248,
          21454
        ],
        [
          249,
          21454
        ],
        [
          256,
          21421
        ],
        [
          257,
          21421
        ],
        [
          264,
          21385
        ],
        [
          265,
          21385
        ],
        [
          280,
          21356
        ],
        [
          281,
          21356
        ],
        [
          304,
          21321
        ],
        [
          305,
          21321
        ],
        [
          320,
          21292
        ],
        [
          321,
          21292
        ],
        [
          4000,
          21292
        ]
      ],
      "avg_iter_time_non_exch_micros": 27.256287,
      "avg_iter_time_exch_micros": 182.9439,
      "duration_millis": 189
    },
    {
      "run_number": 1,
      "found_optimal_tour": false,
      "shortest_found_tour": 21388,
      "iteration_reached": 4000,
      "shortest_iteration_tours": [
        [
          1,
          26139
        ],
        [
          6,
          26098
        ],
        [
          8,
          24698
        ],
        [
          9,
          25465
        ],
        [
          12,
          25396
        ],
        [
          16,
          23864
        ],
        [
          17,
          25334
        ],
        [
          25,
          25271
        ],
        [
          33,
          24601
        ],
        [
          35,
          24401
        ],
        [
          43,
          24315
        ],
        [
          48,
          23567
        ],
        [
          53,
          24205
        ],
        [
          57,
          23567
        ],
        [
          64,
          23113
        ],
        [
          65,
          23460
        ],
        [
          73,
          23363
        ],
        [
          80,
          22849
        ],
        [
          81,
          23171
        ],
        [
          88,
          22363
        ],
        [
          96,
          22351
        ],
        [
          97,
          22363
        ],
        [
          104,
          22194
        ],
        [
          105,
          22246
        ],
        [
          113,
          22194
        ],
        [
          120,
          22066
        ],
        [
          121,
          22066
        ],
        [
          128,
          21975
        ],
        [
          129,
          21975
        ],
        [
          136,
          21963
        ],
        [
          137,
          21967
        ],
        [
          145,
          21963
        ],
        [
          160,
          21813
        ],
        [
          161,
          21813
        ],
        [
          166,
          21724
        ],
        [
          168,
          21724
        ],
        [
          176,
          21705
        ],
        [
          177,
          21705
        ],
        [
          208,
          21616
        ],
        [
          209,
          21616
        ],
        [
          224,
          21603
        ],
        [
          233,
          21603
        ],
        [
          238,
          21591
        ],
        [
          240,
          21591
        ],
        [
          288,
          21460
        ],
        [
          289,
          21574
        ],
        [
          291,
          21535
        ],
        [
          305,
          21460
        ],
        [
          3888,
          21388
        ],
        [
          3889,
          21388
        ],
        [
          4000,
          21388
        ]
      ],
      "avg_iter_time_non_exch_micros": 27.03143,
      "avg_iter_time_exch_micros": 180.62125,
      "duration_millis": 187
    },
    {
      "run_number": 2,
      "found_optimal_tour": false,
      "shortest_found_tour": 21379,
      "iteration_reached": 4000,
      "shortest_iteration_tours": [
        [
          3,
          25933
        ],
        [
          4,
          25862
        ],
        [
          5,
          25641
        ],
        [
          8,
          25257
        ],
        [
          9,
          25289
        ],
        [
          12,
          24749
        ],
        [
          16,
          24749
        ],
        [
          17,
          24366
        ],
        [
          24,
          24366
        ],
        [
          30,
          24274
        ],
        [
          32,
          24191
        ],
        [
          40,
          23805
        ],
        [
          41,
          23805
        ],
        [
          64,
          23528
        ],
        [
          72,
          23020
        ],
        [
          73,
          23793
        ],
        [
          80,
          23445
        ],
        [
          87,
          23228
        ],
        [
          96,
          22907
        ],
        [
          97,
          23087
        ],
        [
          104,
          22813
        ],
        [
          112,
          22777
        ],
        [
          113,
          23078
        ],
        [
          120,
          22510
        ],
        [
          121,
          22777
        ],
        [
          129,
          22510
        ],
        [
          136,
          22434
        ],
        [
          152,
          22428
        ],
        [
          153,
          22428
        ],
        [
          160,
          22359
        ],
        [
          161,
          22383
        ],
        [
          166,
          22367
        ],
        [
          168,
          22284
        ],
        [
          169,
          22356
        ],
        [
          184,
          22222
        ],
        [
          185,
          22284
        ],
        [
          189,
          22220
        ],
        [
          192,
          22125
        ],
        [
          200,
          21939
        ],
        [
          201,
          22125
        ],
        [
          209,
          22012
        ],
        [
          217,
          21939
        ],
        [
          232,
          21918
        ],
        [
          233,
          21918
        ],
        [
          256,
          21793
        ],
        [
          261,
          21752
        ],
        [
          264,
          21752
        ],
        [
          296,
          21731
        ],
        [
          297,
          21731
        ],
        [
          298,
          21725
        ],
        [
          304,
          21725
        ],
        [
          328,
          21652
        ],
        [
          329,
          21652
        ],
        [
          392,
          21625
        ],
        [
          393,
          21625
        ],
        [
          416,
          21525
        ],
        [
          417,
          21604
        ],
        [
          425,
          21525
        ],
        [
          464,
          21522
        ],
        [
          465,
          21522
        ],
        [
          480,
          21492
        ],
        [
          481,
          21492
        ],
        [
          520,
          21481
        ],
        [
          521,
          21481
        ],
        [
          536,
          21417
        ],
        [
          537,
          21425
        ],
        [
          551,
          21417
        ],
        [
          592,
          21379
        ],
        [
          593,
          21379
        ],
        [
          4000,
          21379
        ]
      ],
      "avg_iter_time_non_exch_micros": 27.164286,
      "avg_iter_time_exch_micros": 181.10622,
      "duration_millis": 187
    },
    {
      "run_number": 3,
      "found_optimal_tour": false,
      "shortest_found_tour": 21292,
      "iteration_reached": 4000,
      "shortest_iteration_tours": [
        [
          8,
          24663
        ],
        [
          9,
          24698
        ],
        [
          15,
          24238
        ],
        [
          16,
          24238
        ],
        [
          18,
          24093
        ],
        [
          22,
          24022
        ],
        [
          24,
          24022
        ],
        [
          30,
          23910
        ],
        [
          32,
          23910
        ],
        [
          48,
          23245
        ],
        [
          49,
          23706
        ],
        [
          57,
          23245
        ],
        [
          72,
          22844
        ],
        [
          73,
          22844
        ],
        [
          80,
          22808
        ],
        [
          88,
          22673
        ],
        [
          96,
          22672
        ],
        [
          97,
          22673
        ],
        [
          104,
          22613
        ],
        [
          105,
          22613
        ],
        [
          108,
          22439
        ],
        [
          112,
          22379
        ],
        [
          120,
          22208
        ],
        [
          121,
          22381
        ],
        [
          122,
          22377
        ],
        [
          127,
          22345
        ],
        [
          136,
          22172
        ],
        [
          137,
          22208
        ],
        [
          144,
          22126
        ],
        [
          145,
          22107
        ],
        [
          152,
          22104
        ],
        [
          160,
          21953
        ],
        [
          161,
          22045
        ],
        [
          169,
          21953
        ],
        [
          176,
          21908
        ],
        [
          184,
          21714
        ],
        [
          185,
          21714
        ],
        [
          200,
          21687
        ],
        [
          201,
          21687
        ],
        [
          216,
          21625
        ],
        [
          217,
          21625
        ],
        [
          240,
          21614
        ],
        [
          241,
          21614
        ],
        [
          256,
          21479
        ],
        [
          257,
          21541
        ],
        [
          265,
          21490
        ],
        [
          273,
          21479
        ],
        [
          288,
          21436
        ],
        [
          289,
          21436
        ],
        [
          312,
          21354
        ],
        [
          313,
          21374
        ],
        [
          329,
          21354
        ],
        [
          360,
          21292
        ],
        [
          361,
          21292
        ],
        [
          4000,
          21292
        ]
      ],
      "avg_iter_time_non_exch_micros": 27.308,
      "avg_iter_time_exch_micros": 179.62524,
      "duration_millis": 187
    },
    {
      "run_number": 4,
      "found_optimal_tour": true,
      "shortest_found_tour": 21320,
      "iteration_reached": 2272,
      "shortest_iteration_tours": [
        [
          8,
          24698
        ],
        [
          9,
          24839
        ],
        [
          13,
          24726
        ],
        [
          16,
          24675
        ],
        [
          19,
          24397
        ],
        [
          24,
          24384
        ],
        [
          26,
          24316
        ],
        [
          32,
          24316
        ],
        [
          34,
          24179
        ],
        [
          40,
          23797
        ],
        [
          42,
          24173
        ],
        [
          44,
          24133
        ],
        [
          48,
          23422
        ],
        [
          49,
          23422
        ],
        [
          64,
          23211
        ],
        [
          65,
          23339
        ],
        [
          72,
          23199
        ],
        [
          73,
          23199
        ],
        [
          88,
          23103
        ],
        [
          96,
          22981
        ],
        [
          97,
          22981
        ],
        [
          104,
          22695
        ],
        [
          105,
          22869
        ],
        [
          112,
          22659
        ],
        [
          113,
          22846
        ],
        [
          119,
          22747
        ],
        [
          122,
          22632
        ],
        [
          128,
          22472
        ],
        [
          130,
          22563
        ],
        [
          131,
          22559
        ],
        [
          136,
          22431
        ],
        [
          137,
          22438
        ],
        [
          144,
          22359
        ],
        [
          152,
          22278
        ],
        [
          160,
          22237
        ],
        [
          176,
          22175
        ],
        [
          177,
          22175
        ],
        [
          194,
          22061
        ],
        [
          200,
          22061
        ],
        [
          216,
          22008
        ],
        [
          220,
          21999
        ],
        [
          224,
          21999
        ],
        [
          241,
          21987
        ],
        [
          248,
          21987
        ],
        [
          256,
          21937
        ],
        [
          257,
          21978
        ],
        [
          273,
          21958
        ],
        [
          280,
          21901
        ],
        [
          281,
          21937
        ],
        [
          288,
          21840
        ],
        [
          289,
          21901
        ],
        [
          297,
          21840
        ],
        [
          312,
          21739
        ],
        [
          313,
          21825
        ],
        [
          321,
          21739
        ],
        [
          329,
          21718
        ],
        [
          336,
          21708
        ],
        [
          345,
          21708
        ],
        [
          360,
          21687
        ],
        [
          361,
          21687
        ],
        [
          376,
          21654
        ],
        [
          377,
          21654
        ],
        [
          384,
          21590
        ],
        [
          393,
          21590
        ],
        [
          401,
          21517
        ],
        [
          408,
          21517
        ],
        [
          411,
          21468
        ],
        [
          416,
          21468
        ],
        [
          423,
          21416
        ],
        [
          424,
          21416
        ],
        [
          464,
          21389
        ],
        [
          465,
          21389
        ],
        [
          2192,
          21320
        ],
        [
          2193,
          21320
        ],
        [
          2272,
          21282
        ]
      ],
      "avg_iter_time_non_exch_micros": 28.769115,
      "avg_iter_time_exch_micros": 184.07068,
      "duration_millis": 110
    },
    {
      "run_number": 5,
      "found_optimal_tour": false,
      "shortest_found_tour": 21305,
      "iteration_reached": 4000,
      "shortest_iteration_tours": [
        [
          4,
          24891
        ],
        [
          8,
          24891
        ],
        [
          16,
          24371
        ],
        [
          17,
          24211
        ],
        [
          24,
          24211
        ],
        [
          31,
          24209
        ],
        [
          32,
          23819
        ],
        [
          33,
          23819
        ],
        [
          40,
          23603
        ],
        [
          48,
          23445
        ],
        [
          50,
          23475
        ],
        [
          57,
          23000
        ],
        [
          64,
          23000
        ],
        [
          72,
          22771
        ],
        [
          73,
          22771
        ],
        [
          96,
          22521
        ],
        [
          97,
          22521
        ],
        [
          104,
          22459
        ],
        [
          105,
          22459
        ],
        [
          108,
          22360
        ],
        [
          112,
          22321
        ],
        [
          113,
          22297
        ],
        [
          120,
          22297
        ],
        [
          128,
          22174
        ],
        [
          130,
          22271
        ],
        [
          136,
          22144
        ],
        [
          139,
          22252
        ],
        [
          144,
          21913
        ],
        [
          145,
          22144
        ],
        [
          150,
          21902
        ],
        [
          152,
          21902
        ],
        [
          168,
          21809
        ],
        [
          177,
          21809
        ],
        [
          184,
          21800
        ],
        [
          186,
          21800
        ],
        [
          192,
          21777
        ],
        [
          193,
          21773
        ],
        [
          200,
          21696
        ],
        [
          208,
          21678
        ],
        [
          217,
          21696
        ],
        [
          224,
          21675
        ],
        [
          225,
          21678
        ],
        [
          233,
          21675
        ],
        [
          240,
          21651
        ],
        [
          241,
          21651
        ],
        [
          248,
          21615
        ],
        [
          249,
          21615
        ],
        [
          264,
          21594
        ],
        [
          265,
          21594
        ],
        [
          272,
          21542
        ],
        [
          273,
          21542
        ],
        [
          288,
          21480
        ],
        [
          289,
          21480
        ],
        [
          302,
          21381
        ],
        [
          304,
          21381
        ],
        [
          2504,
          21315
        ],
        [
          2505,
          21315
        ],
        [
          2669,
          21305
        ],
        [
          2672,
          21305
        ],
        [
          4000,
          21305
        ]
      ],
      "avg_iter_time_non_exch_micros": 26.869429,
      "avg_iter_time_exch_micros": 180.87175,
      "duration_millis": 186
    },
    {
      "run_number": 6,
      "found_optimal_tour": true,
      "shortest_found_tour": 21334,
      "iteration_reached": 408,
      "shortest_iteration_tours": [
        [
          5,
          25738
        ],
        [
          8,
          24616
        ],
        [
          9,
          25271
        ],
        [
          16,
          24922
        ],
        [
          24,
          24026
        ],
        [
          25,
          23990
        ],
        [
          32,
          23650
        ],
        [
          40,
          23603
        ],
        [
          41,
          23650
        ],
        [
          48,
          23508
        ],
        [
          49,
          23603
        ],
        [
          64,
          23374
        ],
        [
          65,
          23496
        ],
        [
          72,
          23116
        ],
        [
          76,
          23360
        ],
        [
          78,
          23322
        ],
        [
          80,
          22662
        ],
        [
          81,
          23071
        ],
        [
          96,
          22563
        ],
        [
          97,
          22662
        ],
        [
          121,
          22563
        ],
        [
          128,
          22487
        ],
        [
          136,
          22536
        ],
        [
          144,
          22423
        ],
        [
          152,
          22396
        ],
        [
          153,
          22423
        ],
        [
          161,
          22396
        ],
        [
          168,
          22156
        ],
        [
          169,
          22359
        ],
        [
          176,
          22129
        ],
        [
          177,
          22285
        ],
        [
          188,
          22252
        ],
        [
          192,
          22053
        ],
        [
          201,
          22093
        ],
        [
          208,
          22017
        ],
        [
          217,
          22048
        ],
        [
          224,
          21979
        ],
        [
          225,
          21979
        ],
        [
          232,
          21952
        ],
        [
          239,
          21972
        ],
        [
          240,
          21767
        ],
        [
          249,
          21767
        ],
        [
          254,
          21555
        ],
        [
          256,
          21555
        ],
        [
          272,
          21543
        ],
        [
          273,
          21543
        ],
        [
          280,
          21481
        ],
        [
          281,
          21481
        ],
        [
          296,
          21445
        ],
        [
          297,
          21445
        ],
        [
          320,
          21443
        ],
        [
          321,
          21346
        ],
        [
          328,
          21346
        ],
        [
          360,
          21334
        ],
        [
          408,
          21282
        ]
      ],
      "avg_iter_time_non_exch_micros": 33.82073,
      "avg_iter_time_exch_micros": 203.0,
      "duration_millis": 22
    },
    {
      "run_number": 7,
      "found_optimal_tour": true,
      "shortest_found_tour": 21308,
      "iteration_reached": 656,
      "shortest_iteration_tours": [
        [
          8,
          24529
        ],
        [
          16,
          24227
        ],
        [
          24,
          24213
        ],
        [
          25,
          24213
        ],
        [
          32,
          23964
        ],
        [
          42,
          23961
        ],
        [
          48,
          23961
        ],
        [
          49,
          23874
        ],
        [
          52,
          23775
        ],
        [
          56,
          23572
        ],
        [
          57,
          23572
        ],
        [
          64,
          23442
        ],
        [
          68,
          23446
        ],
        [
          72,
          23364
        ],
        [
          73,
          23369
        ],
        [
          80,
          23169
        ],
        [
          88,
          23093
        ],
        [
          89,
          23364
        ],
        [
          96,
          22980
        ],
        [
          97,
          23093
        ],
        [
          104,
          22882
        ],
        [
          105,
          22980
        ],
        [
          116,
          22899
        ],
        [
          120,
          22688
        ],
        [
          129,
          22724
        ],
        [
          144,
          22525
        ],
        [
          145,
          22705
        ],
        [
          146,
          22663
        ],
        [
          152,
          22504
        ],
        [
          153,
          22525
        ],
        [
          160,
          22442
        ],
        [
          161,
          22504
        ],
        [
          177,
          22463
        ],
        [
          182,
          22412
        ],
        [
          184,
          22412
        ],
        [
          200,
          22309
        ],
        [
          208,
          22184
        ],
        [
          209,
          22309
        ],
        [
          211,
          22265
        ],
        [
          217,
          22249
        ],
        [
          225,
          22184
        ],
        [
          256,
          22141
        ],
        [
          257,
          22141
        ],
        [
          280,
          22014
        ],
        [
          281,
          22017
        ],
        [
          289,
          22014
        ],
        [
          296,
          21955
        ],
        [
          297,
          21955
        ],
        [
          328,
          21949
        ],
        [
          329,
          21949
        ],
        [
          336,
          21850
        ],
        [
          337,
          21850
        ],
        [
          384,
          21844
        ],
        [
          385,
          21844
        ],
        [
          392,
          21774
        ],
        [
          393,
          21774
        ],
        [
          411,
          21722
        ],
        [
          416,
          21698
        ],
        [
          425,
          21698
        ],
        [
          448,
          21567
        ],
        [
          449,
          21694
        ],
        [
          457,
          21567
        ],
        [
          472,
          21564
        ],
        [
          473,
          21564
        ],
        [
          480,
          21491
        ],
        [
          481,
          21491
        ],
        [
          488,
          21464
        ],
        [
          489,
          21464
        ],
        [
          520,
          21438
        ],
        [
          521,
          21438
        ],
        [
          573,
          21411
        ],
        [
          576,
          21411
        ],
        [
          592,
          21335
        ],
        [
          593,
          21335
        ],
        [
          624,
          21308
        ],
        [
          625,
          21308
        ],
        [
          656,
          21282
        ]
      ],
      "avg_iter_time_non_exch_micros": 33.559235,
      "avg_iter_time_exch_micros": 189.12346,
      "duration_millis": 35
    },
    {
      "run_number": 8,
      "found_optimal_tour": false,
      "shortest_found_tour": 21292,
      "iteration_reached": 4000,
      "shortest_iteration_tours": [
        [
          1,
          24252
        ],
        [
          8,
          24252
        ],
        [
          24,
          24166
        ],
        [
          32,
          23788
        ],
        [
          40,
          23546
        ],
        [
          42,
          24251
        ],
        [
          49,
          23788
        ],
        [
          56,
          23125
        ],
        [
          57,
          23125
        ],
        [
          69,
          23077
        ],
        [
          72,
          23077
        ],
        [
          80,
          23044
        ],
        [
          81,
          23056
        ],
        [
          86,
          22856
        ],
        [
          88,
          22230
        ],
        [
          93,
          22817
        ],
        [
          104,
          22154
        ],
        [
          105,
          22154
        ],
        [
          112,
          22036
        ],
        [
          118,
          22118
        ],
        [
          120,
          21960
        ],
        [
          137,
          22036
        ],
        [
          144,
          21950
        ],
        [
          145,
          21960
        ],
        [
          152,
          21859
        ],
        [
          160,
          21783
        ],
        [
          161,
          21950
        ],
        [
          169,
          21859
        ],
        [
          176,
          21756
        ],
        [
          177,
          21783
        ],
        [
          179,
          21702
        ],
        [
          184,
          21700
        ],
        [
          192,
          21597
        ],
        [
          201,
          21597
        ],
        [
          213,
          21559
        ],
        [
          216,
          21433
        ],
        [
          225,
          21433
        ],
        [
          240,
          21425
        ],
        [
          241,
          21427
        ],
        [
          249,
          21425
        ],
        [
          280,
          21397
        ],
        [
          281,
          21389
        ],
        [
          288,
          21389
        ],
        [
          984,
          21353
        ],
        [
          985,
          21353
        ],
        [
          1032,
          21344
        ],
        [
          1033,
          21344
        ],
        [
          1072,
          21292
        ],
        [
          1073,
          21292
        ],
        [
          4000,
          21292
        ]
      ],
      "avg_iter_time_non_exch_micros": 26.99257,
      "avg_iter_time_exch_micros": 179.6513,
      "duration_millis": 186
    },
    {
      "run_number": 9,
      "found_optimal_tour": true,
      "shortest_found_tour": 21295,
      "iteration_reached": 1624,
      "shortest_iteration_tours": [
        [
          1,
          26151
        ],
        [
          7,
          26144
        ],
        [
          8,
          24459
        ],
        [
          9,
          25597
        ],
        [
          10,
          25545
        ],
        [
          11,
          25314
        ],
        [
          16,
          24315
        ],
        [
          17,
          24698
        ],
        [
          24,
          24218
        ],
        [
          25,
          24226
        ],
        [
          27,
          24169
        ],
        [
          32,
          23692
        ],
        [
          33,
          24048
        ],
        [
          41,
          23692
        ],
        [
          48,
          23654
        ],
        [
          49,
          23654
        ],
        [
          56,
          23575
        ],
        [
          64,
          23308
        ],
        [
          65,
          23489
        ],
        [
          67,
          23476
        ],
        [
          72,
          23221
        ],
        [
          81,
          23224
        ],
        [
          88,
          22876
        ],
        [
          94,
          23063
        ],
        [
          96,
          22371
        ],
        [
          97,
          22371
        ],
        [
          112,
          22302
        ],
        [
          121,
          22302
        ],
        [
          128,
          22244
        ],
        [
          129,
          22258
        ],
        [
          137,
          22244
        ],
        [
          143,
          22177
        ],
        [
          144,
          22119
        ],
        [
          145,
          22119
        ],
        [
          160,
          21938
        ],
        [
          169,
          21938
        ],
        [
          176,
          21865
        ],
        [
          184,
          21744
        ],
        [
          185,
          21744
        ],
        [
          200,
          21719
        ],
        [
          201,
          21719
        ],
        [
          208,
          21594
        ],
        [
          209,
          21594
        ],
        [
          256,
          21555
        ],
        [
          257,
          21555
        ],
        [
          264,
          21538
        ],
        [
          265,
          21538
        ],
        [
          272,
          21517
        ],
        [
          273,
          21530
        ],
        [
          281,
          21517
        ],
        [
          298,
          21461
        ],
        [
          304,
          21461
        ],
        [
          328,
          21416
        ],
        [
          329,
          21416
        ],
        [
          352,
          21389
        ],
        [
          353,
          21389
        ],
        [
          1552,
          21336
        ],
        [
          1553,
          21336
        ],
        [
          1568,
          21309
        ],
        [
          1569,
          21309
        ],
        [
          1608,
          21295
        ],
        [
          1609,
          21295
        ],
        [
          1624,
          21282
        ]
      ],
      "avg_iter_time_non_exch_micros": 28.78325,
      "avg_iter_time_exch_micros": 180.9802,
      "duration_millis": 78
    }
  ]
}