{
  "bench_config": {
    "process_count": 4,
    "problem": {
      "name": "kroA200",
      "optimal_length": 29368
    },
    "algorithm": "CABC",
    "algorithm_constants": {
      "max_iterations": 4000,
      "colony_size": 80,
      "exchange_generations": 4,
      "nl_max": 5,
      "p_cp": 0.8,
      "p_rc": 0.5,
      "p_l": 0.2,
      "l_min": 2,
      "l_max_mul": 0.5,
      "r": 1.0,
      "capital_l": 4.0,
      "lowercase_q": 3,
      "k": 16.0
    },
    "benchmark_start_time_millis": 1685256272505,
    "repeat_times": 10
  },
  "benchmark_duration_millis": 19944,
  "run_results": [
    {
      "run_number": 0,
      "found_optimal_tour": false,
      "shortest_found_tour": 29550,
      "iteration_reached": 4000,
      "shortest_iteration_tours": [
        [
          1,
          34543
        ],
        [
          12,
          34527
        ],
        [
          16,
          34358
        ],
        [
          20,
          34205
        ],
        [
          32,
          34149
        ],
        [
          36,
          34108
        ],
        [
          38,
          33949
        ],
        [
          40,
          33739
        ],
        [
          52,
          33684
        ],
        [
          56,
          33588
        ],
        [
          60,
          33335
        ],
        [
          64,
          33300
        ],
        [
          72,
          33245
        ],
        [
          76,
          33051
        ],
        [
          80,
          32996
        ],
        [
          84,
          32893
        ],
        [
          92,
          32882
        ],
        [
          96,
          32826
        ],
        [
          104,
          32242
        ],
        [
          111,
          32108
        ],
        [
          115,
          32079
        ],
        [
          124,
          31716
        ],
        [
          128,
          31709
        ],
        [
          132,
          31471
        ],
        [
          136,
          31450
        ],
        [
          140,
          31268
        ],
        [
          152,
          31085
        ],
        [
          164,
          31028
        ],
        [
          172,
          30903
        ],
        [
          176,
          30896
        ],
        [
          184,
          30885
        ],
        [
          189,
          30799
        ],
        [
          192,
          30776
        ],
        [
          198,
          30672
        ],
        [
          212,
          30597
        ],
        [
          220,
          30576
        ],
        [
          224,
          30568
        ],
        [
          228,
          30566
        ],
        [
          229,
          30562
        ],
        [
          231,
          30444
        ],
        [
          244,
          30351
        ],
        [
          279,
          30294
        ],
        [
          288,
          30289
        ],
        [
          289,
          30274
        ],
        [
          304,
          30264
        ],
        [
          320,
          30183
        ],
        [
          328,
          30162
        ],
        [
          336,
          30160
        ],
        [
          340,
          30124
        ],
        [
          352,
          30071
        ],
        [
          372,
          30016
        ],
        [
          408,
          30013
        ],
        [
          418,
          30009
        ],
        [
          420,
          29981
        ],
        [
          464,
          29955
        ],
        [
          480,
          29931
        ],
        [
          520,
          29905
        ],
        [
          549,
          29903
        ],
        [
          632,
          29878
        ],
        [
          656,
          29856
        ],
        [
          668,
          29852
        ],
        [
          681,
          29845
        ],
        [
          712,
          29843
        ],
        [
          732,
          29830
        ],
        [
          784,
          29828
        ],
        [
          798,
          29823
        ],
        [
          816,
          29821
        ],
        [
          836,
          29813
        ],
        [
          868,
          29791
        ],
        [
          1036,
          29759
        ],
        [
          1047,
          29683
        ],
        [
          1064,
          29559
        ],
        [
          1072,
          29550
        ],
        [
          4000,
          29550
        ]
      ],
      "avg_iter_time_non_exch_micros": 384.9,
      "avg_iter_time_exch_micros": 842.37537,
      "duration_millis": 1999
    },
    {
      "run_number": 1,
      "found_optimal_tour": false,
      "shortest_found_tour": 29626,
      "iteration_reached": 4000,
      "shortest_iteration_tours": [
        [
          1,
          35006
        ],
        [
          4,
          34543
        ],
        [
          8,
          34496
        ],
        [
          10,
          34358
        ],
        [
          12,
          34290
        ],
        [
          16,
          34236
        ],
        [
          24,
          33855
        ],
        [
          28,
          33845
        ],
        [
          32,
          33822
        ],
        [
          34,
          33792
        ],
        [
          36,
          33695
        ],
        [
          40,
          33178
        ],
        [
          53,
          33164
        ],
        [
          58,
          33130
        ],
        [
          68,
          32889
        ],
        [
          76,
          32805
        ],
        [
          80,
          32471
        ],
        [
          88,
          32380
        ],
        [
          91,
          32282
        ],
        [
          100,
          32079
        ],
        [
          110,
          32046
        ],
        [
          112,
          31914
        ],
        [
          115,
          31881
        ],
        [
          118,
          31860
        ],
        [
          125,
          31780
        ],
        [
          134,
          31716
        ],
        [
          142,
          31688
        ],
        [
          144,
          31679
        ],
        [
          146,
          31619
        ],
        [
          152,
          31192
        ],
        [
          182,
          31087
        ],
        [
          200,
          30931
        ],
        [
          220,
          30907
        ],
        [
          232,
          30870
        ],
        [
          240,
          30812
        ],
        [
          244,
          30714
        ],
        [
          256,
          30678
        ],
        [
          264,
          30572
        ],
        [
          288,
          30570
        ],
        [
          296,
          30549
        ],
        [
          298,
          30537
        ],
        [
          309,
          30418
        ],
        [
          340,
          30359
        ],
        [
          348,
          30338
        ],
        [
          356,
          30317
        ],
        [
          364,
          30313
        ],
        [
          368,
          30291
        ],
        [
          372,
          30209
        ],
        [
          408,
          30131
        ],
        [
          436,
          30120
        ],
        [
          456,
          30040
        ],
        [
          472,
          30033
        ],
        [
          492,
          30011
        ],
        [
          503,
          30004
        ],
        [
          512,
          30000
        ],
        [
          513,
          29953
        ],
        [
          535,
          29930
        ],
        [
          536,
          29922
        ],
        [
          560,
          29917
        ],
        [
          564,
          29895
        ],
        [
          575,
          29842
        ],
        [
          592,
          29828
        ],
        [
          600,
          29821
        ],
        [
          616,
          29807
        ],
        [
          628,
          29735
        ],
        [
          644,
          29715
        ],
        [
          708,
          29711
        ],
        [
          724,
          29709
        ],
        [
          773,
          29679
        ],
        [
          826,
          29672
        ],
        [
          848,
          29657
        ],
        [
          884,
          29654
        ],
        [
          944,
          29650
        ],
        [
          992,
          29647
        ],
        [
          1008,
          29629
        ],
        [
          1032,
          29626
        ],
        [
          4000,
          29626
        ]
      ],
      "avg_iter_time_non_exch_micros": 391.17532,
      "avg_iter_time_exch_micros": 767.4384,
      "duration_millis": 1943
    },
    {
      "run_number": 2,
      "found_optimal_tour": false,
      "shortest_found_tour": 29524,
      "iteration_reached": 4000,
      "shortest_iteration_tours": [
        [
          1,
          34543
        ],
        [
          11,
          34227
        ],
        [
          19,
          34056
        ],
        [
          28,
          33723
        ],
        [
          32,
          33164
        ],
        [
          52,
          33125
        ],
        [
          59,
          32682
        ],
        [
          68,
          32655
        ],
        [
          71,
          32627
        ],
        [
          80,
          32598
        ],
        [
          84,
          32543
        ],
        [
          92,
          32350
        ],
        [
          104,
          32319
        ],
        [
          116,
          32138
        ],
        [
          120,
          32034
        ],
        [
          136,
          31850
        ],
        [
          146,
          31712
        ],
        [
          148,
          31655
        ],
        [
          160,
          31499
        ],
        [
          168,
          31472
        ],
        [
          176,
          31407
        ],
        [
          180,
          31188
        ],
        [
          212,
          31187
        ],
        [
          213,
          31115
        ],
        [
          220,
          31104
        ],
        [
          228,
          30997
        ],
        [
          236,
          30888
        ],
        [
          240,
          30849
        ],
        [
          248,
          30781
        ],
        [
          252,
          30740
        ],
        [
          260,
          30737
        ],
        [
          268,
          30669
        ],
        [
          272,
          30668
        ],
        [
          287,
          30583
        ],
        [
          304,
          30512
        ],
        [
          316,
          30455
        ],
        [
          328,
          30363
        ],
        [
          340,
          30314
        ],
        [
          348,
          30311
        ],
        [
          356,
          30285
        ],
        [
          372,
          30147
        ],
        [
          388,
          30133
        ],
        [
          400,
          30055
        ],
        [
          425,
          30020
        ],
        [
          428,
          29987
        ],
        [
          434,
          29981
        ],
        [
          464,
          29927
        ],
        [
          491,
          29889
        ],
        [
          508,
          29875
        ],
        [
          520,
          29838
        ],
        [
          540,
          29833
        ],
        [
          546,
          29826
        ],
        [
          556,
          29796
        ],
        [
          576,
          29795
        ],
        [
          590,
          29792
        ],
        [
          592,
          29767
        ],
        [
          600,
          29760
        ],
        [
          604,
          29725
        ],
        [
          608,
          29721
        ],
        [
          628,
          29695
        ],
        [
          648,
          29688
        ],
        [
          659,
          29653
        ],
        [
          716,
          29618
        ],
        [
          732,
          29596
        ],
        [
          739,
          29575
        ],
        [
          764,
          29574
        ],
        [
          808,
          29563
        ],
        [
          862,
          29557
        ],
        [
          884,
          29537
        ],
        [
          918,
          29531
        ],
        [
          1204,
          29524
        ],
        [
          4000,
          29524
        ]
      ],
      "avg_iter_time_non_exch_micros": 387.97266,
      "avg_iter_time_exch_micros": 767.03906,
      "duration_millis": 1933
    },
    {
      "run_number": 3,
      "found_optimal_tour": false,
      "shortest_found_tour": 29503,
      "iteration_reached": 4000,
      "shortest_iteration_tours": [
        [
          1,
          34543
        ],
        [
          6,
          34292
        ],
        [
          8,
          34209
        ],
        [
          12,
          34206
        ],
        [
          20,
          34050
        ],
        [
          24,
          33819
        ],
        [
          35,
          33702
        ],
        [
          40,
          33547
        ],
        [
          48,
          33105
        ],
        [
          53,
          33035
        ],
        [
          60,
          33030
        ],
        [
          64,
          32896
        ],
        [
          68,
          32719
        ],
        [
          80,
          32633
        ],
        [
          84,
          32607
        ],
        [
          92,
          32433
        ],
        [
          101,
          32412
        ],
        [
          108,
          32277
        ],
        [
          111,
          32249
        ],
        [
          114,
          32171
        ],
        [
          132,
          32158
        ],
        [
          144,
          32150
        ],
        [
          148,
          32032
        ],
        [
          161,
          31997
        ],
        [
          163,
          31988
        ],
        [
          164,
          31926
        ],
        [
          168,
          31871
        ],
        [
          172,
          31807
        ],
        [
          180,
          31655
        ],
        [
          184,
          31634
        ],
        [
          188,
          31508
        ],
        [
          208,
          31480
        ],
        [
          212,
          31478
        ],
        [
          224,
          31454
        ],
        [
          229,
          31377
        ],
        [
          232,
          31322
        ],
        [
          243,
          31262
        ],
        [
          258,
          31258
        ],
        [
          260,
          31227
        ],
        [
          268,
          31188
        ],
        [
          276,
          31072
        ],
        [
          292,
          31041
        ],
        [
          296,
          30930
        ],
        [
          300,
          30727
        ],
        [
          312,
          30550
        ],
        [
          322,
          30517
        ],
        [
          328,
          30348
        ],
        [
          342,
          30346
        ],
        [
          357,
          30313
        ],
        [
          364,
          30311
        ],
        [
          368,
          30308
        ],
        [
          375,
          30172
        ],
        [
          376,
          30135
        ],
        [
          380,
          30124
        ],
        [
          396,
          30095
        ],
        [
          400,
          30087
        ],
        [
          412,
          30052
        ],
        [
          436,
          30020
        ],
        [
          444,
          29987
        ],
        [
          456,
          29982
        ],
        [
          464,
          29939
        ],
        [
          476,
          29931
        ],
        [
          484,
          29901
        ],
        [
          492,
          29836
        ],
        [
          500,
          29806
        ],
        [
          512,
          29803
        ],
        [
          513,
          29798
        ],
        [
          516,
          29793
        ],
        [
          524,
          29765
        ],
        [
          539,
          29723
        ],
        [
          560,
          29662
        ],
        [
          588,
          29615
        ],
        [
          618,
          29594
        ],
        [
          636,
          29584
        ],
        [
          647,
          29567
        ],
        [
          896,
          29553
        ],
        [
          3408,
          29517
        ],
        [
          3512,
          29503
        ],
        [
          4000,
          29503
        ]
      ],
      "avg_iter_time_non_exch_micros": 382.937,
      "avg_iter_time_exch_micros": 757.4124,
      "duration_millis": 1908
    },
    {
      "run_number": 4,
      "found_optimal_tour": false,
      "shortest_found_tour": 29713,
      "iteration_reached": 4000,
      "shortest_iteration_tours": [
        [
          1,
          35206
        ],
        [
          4,
          34543
        ],
        [
          8,
          33929
        ],
        [
          12,
          33872
        ],
        [
          19,
          33846
        ],
        [
          28,
          33781
        ],
        [
          32,
          33654
        ],
        [
          40,
          33481
        ],
        [
          45,
          33471
        ],
        [
          48,
          33396
        ],
        [
          56,
          33307
        ],
        [
          60,
          32461
        ],
        [
          68,
          32357
        ],
        [
          76,
          31935
        ],
        [
          94,
          31719
        ],
        [
          100,
          31710
        ],
        [
          115,
          31681
        ],
        [
          116,
          31554
        ],
        [
          120,
          31462
        ],
        [
          124,
          31455
        ],
        [
          130,
          31366
        ],
        [
          136,
          31116
        ],
        [
          148,
          31056
        ],
        [
          152,
          31055
        ],
        [
          160,
          31041
        ],
        [
          171,
          30986
        ],
        [
          189,
          30927
        ],
        [
          192,
          30744
        ],
        [
          212,
          30735
        ],
        [
          216,
          30689
        ],
        [
          232,
          30667
        ],
        [
          236,
          30648
        ],
        [
          240,
          30471
        ],
        [
          256,
          30457
        ],
        [
          260,
          30447
        ],
        [
          268,
          30393
        ],
        [
          288,
          30205
        ],
        [
          296,
          30179
        ],
        [
          298,
          30172
        ],
        [
          300,
          30170
        ],
        [
          312,
          30163
        ],
        [
          320,
          29998
        ],
        [
          356,
          29972
        ],
        [
          368,
          29956
        ],
        [
          388,
          29935
        ],
        [
          401,
          29839
        ],
        [
          432,
          29823
        ],
        [
          440,
          29797
        ],
        [
          480,
          29734
        ],
        [
          608,
          29727
        ],
        [
          634,
          29720
        ],
        [
          672,
          29713
        ],
        [
          4000,
          29713
        ]
      ],
      "avg_iter_time_non_exch_micros": 395.68466,
      "avg_iter_time_exch_micros": 757.7187,
      "duration_millis": 1947
    },
    {
      "run_number": 5,
      "found_optimal_tour": false,
      "shortest_found_tour": 29562,
      "iteration_reached": 4000,
      "shortest_iteration_tours": [
        [
          1,
          35080
        ],
        [
          4,
          33882
        ],
        [
          8,
          33769
        ],
        [
          12,
          33689
        ],
        [
          16,
          33682
        ],
        [
          20,
          33288
        ],
        [
          28,
          33205
        ],
        [
          36,
          33183
        ],
        [
          40,
          33163
        ],
        [
          44,
          32673
        ],
        [
          64,
          32495
        ],
        [
          72,
          32438
        ],
        [
          80,
          32342
        ],
        [
          88,
          32278
        ],
        [
          98,
          32255
        ],
        [
          100,
          32252
        ],
        [
          104,
          32220
        ],
        [
          108,
          32089
        ],
        [
          115,
          32061
        ],
        [
          124,
          32046
        ],
        [
          128,
          31857
        ],
        [
          140,
          31819
        ],
        [
          142,
          31813
        ],
        [
          145,
          31797
        ],
        [
          146,
          31791
        ],
        [
          150,
          31761
        ],
        [
          152,
          31673
        ],
        [
          160,
          31616
        ],
        [
          164,
          31491
        ],
        [
          176,
          31436
        ],
        [
          180,
          31380
        ],
        [
          184,
          31336
        ],
        [
          188,
          31335
        ],
        [
          200,
          31280
        ],
        [
          208,
          31127
        ],
        [
          220,
          31114
        ],
        [
          223,
          31076
        ],
        [
          240,
          31010
        ],
        [
          244,
          30982
        ],
        [
          248,
          30924
        ],
        [
          252,
          30900
        ],
        [
          264,
          30858
        ],
        [
          268,
          30791
        ],
        [
          272,
          30770
        ],
        [
          276,
          30754
        ],
        [
          280,
          30711
        ],
        [
          292,
          30607
        ],
        [
          302,
          30508
        ],
        [
          312,
          30457
        ],
        [
          316,
          30382
        ],
        [
          328,
          30296
        ],
        [
          336,
          30093
        ],
        [
          344,
          29960
        ],
        [
          360,
          29882
        ],
        [
          368,
          29879
        ],
        [
          372,
          29825
        ],
        [
          392,
          29799
        ],
        [
          404,
          29770
        ],
        [
          416,
          29767
        ],
        [
          420,
          29732
        ],
        [
          468,
          29721
        ],
        [
          484,
          29718
        ],
        [
          497,
          29677
        ],
        [
          563,
          29657
        ],
        [
          576,
          29654
        ],
        [
          596,
          29640
        ],
        [
          601,
          29624
        ],
        [
          640,
          29602
        ],
        [
          687,
          29588
        ],
        [
          940,
          29585
        ],
        [
          980,
          29562
        ],
        [
          4000,
          29562
        ]
      ],
      "avg_iter_time_non_exch_micros": 398.72867,
      "avg_iter_time_exch_micros": 746.1181,
      "duration_millis": 1944
    },
    {
      "run_number": 6,
      "found_optimal_tour": false,
      "shortest_found_tour": 29713,
      "iteration_reached": 4000,
      "shortest_iteration_tours": [
        [
          1,
          35080
        ],
        [
          4,
          34411
        ],
        [
          8,
          34174
        ],
        [
          13,
          34052
        ],
        [
          16,
          33956
        ],
        [
          24,
          33924
        ],
        [
          25,
          33909
        ],
        [
          30,
          33823
        ],
        [
          31,
          33815
        ],
        [
          32,
          33759
        ],
        [
          36,
          33750
        ],
        [
          40,
          33656
        ],
        [
          42,
          33652
        ],
        [
          48,
          32345
        ],
        [
          56,
          32241
        ],
        [
          64,
          32201
        ],
        [
          72,
          32181
        ],
        [
          74,
          31970
        ],
        [
          83,
          31866
        ],
        [
          91,
          31704
        ],
        [
          108,
          31567
        ],
        [
          128,
          31316
        ],
        [
          132,
          31179
        ],
        [
          145,
          31153
        ],
        [
          148,
          31041
        ],
        [
          160,
          31014
        ],
        [
          173,
          30970
        ],
        [
          178,
          30936
        ],
        [
          187,
          30928
        ],
        [
          191,
          30846
        ],
        [
          196,
          30689
        ],
        [
          208,
          30686
        ],
        [
          211,
          30651
        ],
        [
          224,
          30613
        ],
        [
          236,
          30606
        ],
        [
          244,
          30591
        ],
        [
          248,
          30587
        ],
        [
          259,
          30564
        ],
        [
          260,
          30545
        ],
        [
          264,
          30543
        ],
        [
          268,
          30535
        ],
        [
          272,
          30519
        ],
        [
          292,
          30456
        ],
        [
          308,
          30417
        ],
        [
          320,
          30384
        ],
        [
          324,
          30289
        ],
        [
          332,
          30251
        ],
        [
          336,
          30214
        ],
        [
          352,
          30183
        ],
        [
          359,
          30146
        ],
        [
          368,
          30120
        ],
        [
          404,
          30045
        ],
        [
          448,
          30009
        ],
        [
          462,
          30003
        ],
        [
          472,
          29983
        ],
        [
          476,
          29972
        ],
        [
          548,
          29952
        ],
        [
          556,
          29939
        ],
        [
          558,
          29937
        ],
        [
          562,
          29930
        ],
        [
          568,
          29917
        ],
        [
          620,
          29914
        ],
        [
          622,
          29895
        ],
        [
          628,
          29891
        ],
        [
          664,
          29889
        ],
        [
          700,
          29875
        ],
        [
          732,
          29873
        ],
        [
          752,
          29859
        ],
        [
          796,
          29843
        ],
        [
          821,
          29842
        ],
        [
          856,
          29840
        ],
        [
          896,
          29814
        ],
        [
          912,
          29810
        ],
        [
          940,
          29788
        ],
        [
          1012,
          29735
        ],
        [
          1028,
          29713
        ],
        [
          4000,
          29713
        ]
      ],
      "avg_iter_time_non_exch_micros": 391.61768,
      "avg_iter_time_exch_micros": 750.4054,
      "duration_millis": 1927
    },
    {
      "run_number": 7,
      "found_optimal_tour": false,
      "shortest_found_tour": 29833,
      "iteration_reached": 4000,
      "shortest_iteration_tours": [
        [
          1,
          35214
        ],
        [
          4,
          34172
        ],
        [
          12,
          34127
        ],
        [
          16,
          33815
        ],
        [
          24,
          33309
        ],
        [
          28,
          33231
        ],
        [
          47,
          33213
        ],
        [
          48,
          33174
        ],
        [
          52,
          33140
        ],
        [
          56,
          33128
        ],
        [
          62,
          33126
        ],
        [
          64,
          33057
        ],
        [
          66,
          32902
        ],
        [
          75,
          32858
        ],
        [
          84,
          32838
        ],
        [
          88,
          32588
        ],
        [
          104,
          32536
        ],
        [
          108,
          32497
        ],
        [
          112,
          32378
        ],
        [
          115,
          32375
        ],
        [
          121,
          32308
        ],
        [
          128,
          32294
        ],
        [
          132,
          32288
        ],
        [
          140,
          32274
        ],
        [
          144,
          32210
        ],
        [
          150,
          32192
        ],
        [
          153,
          32124
        ],
        [
          168,
          32102
        ],
        [
          180,
          32046
        ],
        [
          188,
          32038
        ],
        [
          192,
          32022
        ],
        [
          195,
          31991
        ],
        [
          204,
          31896
        ],
        [
          216,
          31803
        ],
        [
          217,
          31799
        ],
        [
          224,
          31798
        ],
        [
          228,
          31714
        ],
        [
          248,
          31693
        ],
        [
          252,
          31675
        ],
        [
          256,
          31643
        ],
        [
          260,
          31577
        ],
        [
          266,
          31559
        ],
        [
          268,
          31499
        ],
        [
          280,
          31495
        ],
        [
          284,
          31465
        ],
        [
          286,
          31341
        ],
        [
          292,
          31274
        ],
        [
          313,
          31064
        ],
        [
          332,
          31020
        ],
        [
          336,
          30986
        ],
        [
          344,
          30974
        ],
        [
          348,
          30944
        ],
        [
          364,
          30932
        ],
        [
          368,
          30930
        ],
        [
          372,
          30863
        ],
        [
          384,
          30819
        ],
        [
          388,
          30797
        ],
        [
          396,
          30755
        ],
        [
          400,
          30707
        ],
        [
          412,
          30687
        ],
        [
          416,
          30612
        ],
        [
          426,
          30530
        ],
        [
          444,
          30484
        ],
        [
          452,
          30478
        ],
        [
          468,
          30466
        ],
        [
          472,
          30373
        ],
        [
          488,
          30326
        ],
        [
          492,
          30317
        ],
        [
          500,
          30279
        ],
        [
          512,
          30227
        ],
        [
          539,
          30189
        ],
        [
          560,
          30163
        ],
        [
          564,
          30149
        ],
        [
          592,
          30142
        ],
        [
          606,
          30125
        ],
        [
          636,
          30121
        ],
        [
          648,
          30107
        ],
        [
          656,
          30105
        ],
        [
          660,
          30055
        ],
        [
          688,
          29977
        ],
        [
          716,
          29966
        ],
        [
          744,
          29951
        ],
        [
          775,
          29947
        ],
        [
          776,
          29921
        ],
        [
          820,
          29910
        ],
        [
          844,
          29903
        ],
        [
          972,
          29899
        ],
        [
          1008,
          29891
        ],
        [
          1060,
          29863
        ],
        [
          1094,
          29850
        ],
        [
          1142,
          29846
        ],
        [
          1146,
          29838
        ],
        [
          1176,
          29833
        ],
        [
          4000,
          29833
        ]
      ],
      "avg_iter_time_non_exch_micros": 406.83267,
      "avg_iter_time_exch_micros": 990.5015,
      "duration_millis": 2213
    },
    {
      "run_number": 8,
      "found_optimal_tour": false,
      "shortest_found_tour": 29669,
      "iteration_reached": 4000,
      "shortest_iteration_tours": [
        [
          1,
          34543
        ],
        [
          4,
          34452
        ],
        [
          12,
          34317
        ],
        [
          16,
          34152
        ],
        [
          20,
          33883
        ],
        [
          22,
          33724
        ],
        [
          24,
          33605
        ],
        [
          28,
          33591
        ],
        [
          32,
          33388
        ],
        [
          44,
          33346
        ],
        [
          51,
          33274
        ],
        [
          54,
          33259
        ],
        [
          57,
          32971
        ],
        [
          68,
          32849
        ],
        [
          74,
          32542
        ],
        [
          80,
          32511
        ],
        [
          85,
          32344
        ],
        [
          96,
          32297
        ],
        [
          99,
          32281
        ],
        [
          100,
          32262
        ],
        [
          101,
          32023
        ],
        [
          114,
          31955
        ],
        [
          120,
          31871
        ],
        [
          128,
          31844
        ],
        [
          136,
          31764
        ],
        [
          148,
          31587
        ],
        [
          172,
          31531
        ],
        [
          180,
          31507
        ],
        [
          195,
          31490
        ],
        [
          200,
          31360
        ],
        [
          204,
          31355
        ],
        [
          224,
          31340
        ],
        [
          229,
          31152
        ],
        [
          236,
          31145
        ],
        [
          248,
          31143
        ],
        [
          252,
          31125
        ],
        [
          256,
          31089
        ],
        [
          260,
          31075
        ],
        [
          264,
          31045
        ],
        [
          269,
          30979
        ],
        [
          276,
          30964
        ],
        [
          284,
          30870
        ],
        [
          304,
          30784
        ],
        [
          316,
          30778
        ],
        [
          318,
          30770
        ],
        [
          326,
          30764
        ],
        [
          328,
          30700
        ],
        [
          358,
          30686
        ],
        [
          376,
          30662
        ],
        [
          384,
          30577
        ],
        [
          424,
          30565
        ],
        [
          428,
          30527
        ],
        [
          436,
          30506
        ],
        [
          448,
          30477
        ],
        [
          504,
          30426
        ],
        [
          517,
          30414
        ],
        [
          544,
          30412
        ],
        [
          588,
          30347
        ],
        [
          612,
          30345
        ],
        [
          640,
          30325
        ],
        [
          641,
          30069
        ],
        [
          660,
          30031
        ],
        [
          704,
          30011
        ],
        [
          760,
          29998
        ],
        [
          768,
          29931
        ],
        [
          808,
          29917
        ],
        [
          844,
          29859
        ],
        [
          880,
          29838
        ],
        [
          900,
          29808
        ],
        [
          912,
          29772
        ],
        [
          917,
          29765
        ],
        [
          920,
          29751
        ],
        [
          972,
          29729
        ],
        [
          975,
          29722
        ],
        [
          1004,
          29692
        ],
        [
          1061,
          29689
        ],
        [
          1268,
          29678
        ],
        [
          1324,
          29675
        ],
        [
          1405,
          29674
        ],
        [
          1600,
          29669
        ],
        [
          4000,
          29669
        ]
      ],
      "avg_iter_time_non_exch_micros": 394.78333,
      "avg_iter_time_exch_micros": 819.72675,
      "duration_millis": 2011
    },
    {
      "run_number": 9,
      "found_optimal_tour": false,
      "shortest_found_tour": 29950,
      "iteration_reached": 4000,
      "shortest_iteration_tours": [
        [
          1,
          35080
        ],
        [
          4,
          34543
        ],
        [
          8,
          34486
        ],
        [
          12,
          33183
        ],
        [
          28,
          33085
        ],
        [
          31,
          33078
        ],
        [
          32,
          32927
        ],
        [
          40,
          32746
        ],
        [
          46,
          32704
        ],
        [
          68,
          32509
        ],
        [
          84,
          32324
        ],
        [
          92,
          32108
        ],
        [
          100,
          32030
        ],
        [
          108,
          32015
        ],
        [
          120,
          31925
        ],
        [
          128,
          31822
        ],
        [
          136,
          31806
        ],
        [
          144,
          31728
        ],
        [
          147,
          31709
        ],
        [
          156,
          31663
        ],
        [
          164,
          31506
        ],
        [
          168,
          31459
        ],
        [
          172,
          31409
        ],
        [
          175,
          31405
        ],
        [
          194,
          31261
        ],
        [
          208,
          31135
        ],
        [
          212,
          31115
        ],
        [
          220,
          31044
        ],
        [
          228,
          30971
        ],
        [
          248,
          30899
        ],
        [
          256,
          30859
        ],
        [
          267,
          30718
        ],
        [
          280,
          30624
        ],
        [
          302,
          30552
        ],
        [
          307,
          30388
        ],
        [
          310,
          30360
        ],
        [
          332,
          30340
        ],
        [
          336,
          30232
        ],
        [
          348,
          30199
        ],
        [
          363,
          30192
        ],
        [
          396,
          30172
        ],
        [
          412,
          30170
        ],
        [
          413,
          30120
        ],
        [
          448,
          30117
        ],
        [
          451,
          30098
        ],
        [
          472,
          30059
        ],
        [
          488,
          30040
        ],
        [
          540,
          30039
        ],
        [
          549,
          30020
        ],
        [
          564,
          30019
        ],
        [
          600,
          30016
        ],
        [
          608,
          30015
        ],
        [
          624,
          29999
        ],
        [
          627,
          29996
        ],
        [
          688,
          29995
        ],
        [
          712,
          29989
        ],
        [
          731,
          29976
        ],
        [
          852,
          29962
        ],
        [
          928,
          29957
        ],
        [
          1044,
          29950
        ],
        [
          4000,
          29950
        ]
      ],
      "avg_iter_time_non_exch_micros": 390.19333,
      "avg_iter_time_exch_micros": 840.7087,
      "duration_millis": 2013
    }
  ]
}